Metadata-Version: 2.1
Name: ygetter
Version: 0.0.5
Summary: Getting information about youtube video(s)
Home-page: UNKNOWN
Author: Fred
Author-email: unknown@gmail.com
License: UNKNOWN
Keywords: python,youtube,yt,info,info getter,easy
Platform: UNKNOWN
Classifier: Development Status :: 1 - Planning
Classifier: Intended Audience :: Developers
Classifier: Programming Language :: Python :: 3
Classifier: Operating System :: Unix
Classifier: Operating System :: MacOS :: MacOS X
Classifier: Operating System :: Microsoft :: Windows
